flask_rest_engine/__init__.py
flask_rest_engine/bootstrap.py
flask_rest_engine/devtools.py
flask_rest_engine/handlers/__init__.py
flask_rest_engine/handlers/bootstrap.py
flask_rest_engine/handlers/devtools.py
flask_rest_engine/static/bootstrap/rivendell/.gitignore.jinja2
flask_rest_engine/static/bootstrap/rivendell/Dockerfile.jinja2
flask_rest_engine/static/bootstrap/rivendell/deploy.sh.jinja2
flask_rest_engine/static/bootstrap/rivendell/docker-compose.yml.jinja2
flask_rest_engine/static/bootstrap/rivendell/pytest.ini.jinja2
flask_rest_engine/static/bootstrap/rivendell/requirements.txt.jinja2
flask_rest_engine/static/bootstrap/rivendell/app/__init__.py.jinja2
flask_rest_engine/static/bootstrap/rivendell/app/exts.py.jinja2
flask_rest_engine/static/bootstrap/rivendell/app/run.py.jinja2
flask_rest_engine/static/bootstrap/rivendell/app/configs/__init__.py.jinja2
flask_rest_engine/static/bootstrap/rivendell/app/configs/default.py.jinja2
flask_rest_engine/static/bootstrap/rivendell/app/configs/development.py.jinja2
flask_rest_engine/static/bootstrap/rivendell/app/configs/logger_config.py.jinja2
flask_rest_engine/static/bootstrap/rivendell/app/configs/production.py.jinja2
flask_rest_engine/static/bootstrap/rivendell/app/configs/testing.py.jinja2
flask_rest_engine/static/bootstrap/rivendell/app/core/__init__.py.jinja2
flask_rest_engine/static/bootstrap/rivendell/app/endpoints/__init__.py.jinja2
flask_rest_engine/static/bootstrap/rivendell/app/endpoints/tools.py.jinja2
flask_rest_engine/static/bootstrap/rivendell/app/models/__init__.py.jinja2
flask_rest_engine/static/bootstrap/rivendell/app/models/consts.py.jinja2
flask_rest_engine/static/bootstrap/rivendell/app/schemas/__init__.py.jinja2
flask_rest_engine/static/bootstrap/rivendell/app/services/__init__.py.jinja2
flask_rest_engine/static/bootstrap/rivendell/app/services/tools.py.jinja2
flask_rest_engine/static/bootstrap/rivendell/app/tasks/__init__.py.jinja2
flask_rest_engine-1.0.3.dist-info/LICENSE
flask_rest_engine-1.0.3.dist-info/METADATA
flask_rest_engine-1.0.3.dist-info/WHEEL
flask_rest_engine-1.0.3.dist-info/entry_points.txt
flask_rest_engine-1.0.3.dist-info/top_level.txt
flask_rest_engine-1.0.3.dist-info/RECORD
