Metadata-Version: 2.1
Name: flask-rest-engine
Version: 1.0.3
Summary: Flask-rest-engine - A flask restful API project generator.
Home-page: https://github.com/penghanyuan/flask-rest-engine
Author: Hyria PENG
Author-email: penghanyuan@gmail.com
Classifier: Topic :: Utilities
Classifier: Programming Language :: Python :: 3.6
Classifier: Programming Language :: Python :: 3.7
Classifier: Programming Language :: Python :: 3.8
Classifier: Programming Language :: Python :: 3.9
Classifier: Programming Language :: Python :: 3.10
Classifier: Programming Language :: Python :: Implementation :: CPython
Classifier: License :: OSI Approved :: MIT License
Requires-Python: >=3.6, <4
License-File: LICENSE
Requires-Dist: Click (>=8.1.0)
Requires-Dist: Jinja2 (>=3.1.2)
Requires-Dist: inflect (>=5.6.2)
